README.md
setup.cfg
setup.py
feast_azure_blob_connect/__init__.py
feast_azure_blob_connect/registry_store.py
feast_azure_blob_connect.egg-info/PKG-INFO
feast_azure_blob_connect.egg-info/SOURCES.txt
feast_azure_blob_connect.egg-info/dependency_links.txt
feast_azure_blob_connect.egg-info/requires.txt
feast_azure_blob_connect.egg-info/top_level.txt