Metadata-Version: 2.1
Name: feast-azure-blob-connect
Version: 0.3.0
Summary: A Feast Azure Provider for blob connect only
Author: Microsoft
License: MIT
Platform: UNKNOWN
Classifier: License :: OSI Approved :: MIT License
Classifier: Programming Language :: Python
Classifier: Programming Language :: Python :: 3
Classifier: Programming Language :: Python :: 3.8
Requires-Python: >=3.8.1, <=3.8.15
Provides-Extra: dev
Provides-Extra: snowflake
